pandoc_tex_numbering/__init__.py
pandoc_tex_numbering/docx_list.py
pandoc_tex_numbering/lang_num.py
pandoc_tex_numbering/numbering.py
pandoc_tex_numbering/oxml.py
pandoc_tex_numbering/pandoc_tex_numbering.py
pandoc_tex_numbering-1.3.3.dist-info/METADATA
pandoc_tex_numbering-1.3.3.dist-info/WHEEL
pandoc_tex_numbering-1.3.3.dist-info/entry_points.txt
pandoc_tex_numbering-1.3.3.dist-info/licenses/LICENSE
pandoc_tex_numbering-1.3.3.dist-info/RECORD
