Metadata-Version: 2.4
Name: pandoc-tex-numbering
Version: 1.3.3
Summary: All-in-one pandoc filter for highly flexible numbering and cross referencing of everything in LaTeX.
Project-URL: Documentation, https://github.com/fncokg/pandoc-tex-numbering
Project-URL: Repository, https://github.com/fncokg/pandoc-tex-numbering
Project-URL: Bug Tracker, https://github.com/fncokg/pandoc-tex-numbering/issues
Author-email: Chao Kong <kongchao1998@gmail.com>
License:                     GNU GENERAL PUBLIC LICENSE
License-File: LICENSE
Classifier: Development Status :: 5 - Production/Stable
Classifier: Environment :: Console
Classifier: Programming Language :: Python
Requires-Python: >=3.8
Requires-Dist: panflute
Requires-Dist: pylatexenc
